LICENSE
MANIFEST.in
README.md
requirements.txt
setup.py
realms/__init__.py
realms/commands.py
realms/version.py
realms/config/__init__.py
realms/lib/__init__.py
realms/lib/hook.py
realms/lib/model.py
realms/lib/test.py
realms/lib/util.py
realms/modules/__init__.py
realms/modules/auth/__init__.py
realms/modules/auth/commands.py
realms/modules/auth/forms.py
realms/modules/auth/hooks.py
realms/modules/auth/models.py
realms/modules/auth/tests.py
realms/modules/auth/views.py
realms/modules/search/__init__.py
realms/modules/search/commands.py
realms/modules/search/hooks.py
realms/modules/search/models.py
realms/modules/search/views.py
realms/modules/wiki/__init__.py
realms/modules/wiki/assets.py
realms/modules/wiki/hooks.py
realms/modules/wiki/models.py
realms/modules/wiki/tests.py
realms/modules/wiki/views.py
realms/static/css/style.css
realms/static/fonts/FontAwesome.otf
realms/static/fonts/fontawesome-webfont.eot
realms/static/fonts/fontawesome-webfont.svg
realms/static/fonts/fontawesome-webfont.ttf
realms/static/fonts/fontawesome-webfont.woff
realms/static/img/favicon.ico
realms/static/js/aced.js
realms/static/js/editor.js
realms/static/js/hbs-helpers.js
realms/static/js/html-css-sanitizer-minified.js
realms/static/js/html-sanitizer-minified.js
realms/static/js/html5shiv.js
realms/static/js/main.js
realms/static/js/mdr.js
realms/static/js/respond.js
realms/static/js/collaboration/firepad.js
realms/static/js/collaboration/main.js
realms/static/js/collaboration/togetherjs.js
realms/static/vendor/ace-builds/.bower.json
realms/static/vendor/ace-builds/ChangeLog.txt
realms/static/vendor/ace-builds/LICENSE
realms/static/vendor/ace-builds/README.md
realms/static/vendor/ace-builds/editor.html
realms/static/vendor/ace-builds/kitchen-sink.html
realms/static/vendor/ace-builds/package.json
realms/static/vendor/ace-builds/demo/autocompletion.html
realms/static/vendor/ace-builds/demo/autoresize.html
realms/static/vendor/ace-builds/demo/chromevox.html
realms_wiki.egg-info/PKG-INFO
realms_wiki.egg-info/SOURCES.txt
realms_wiki.egg-info/dependency_links.txt
realms_wiki.egg-info/entry_points.txt
realms_wiki.egg-info/requires.txt
realms_wiki.egg-info/top_level.txt