Metadata-Version: 1.1
Name: realms-wiki
Version: 0.5.4
Summary: Simple git based wiki
Home-page: https://github.com/scragg0x/realms-wiki
Author: Matthew Scragg
Author-email: scragg@gmail.com
License: GPLv2
Platform: any
Classifier: Intended Audience :: Developers
Classifier: License :: OSI Approved :: GNU General Public License v2 (GPLv2)
Classifier: Operating System :: POSIX :: Linux
Classifier: Programming Language :: Python
Classifier: Topic :: Internet :: WWW/HTTP :: Dynamic Content
